tld.py
tld_task-1.0.0.dist-info/METADATA
tld_task-1.0.0.dist-info/RECORD
tld_task-1.0.0.dist-info/WHEEL
tld_task-1.0.0.dist-info/entry_points.txt
tld_task-1.0.0.dist-info/top_level.txt
