Metadata-Version: 2.1
Name: tld-task
Version: 1.0.0
Summary: tld is a tool for people who want to do things, but who want a bit of flexibility.
Home-page: https://github.com/davidlowryduda/tld
Author: David Lowry-Duda
Author-email: davidlowryduda@davidlowryduda.com
License: UNKNOWN
Platform: UNKNOWN
Classifier: Programming Language :: Python :: 3.6
Classifier: Programming Language :: Python :: 3.7
Classifier: License :: OSI Approved :: MIT License
Classifier: Operating System :: OS Independent
Classifier: Environment :: Console
